SLIX/__init__.py
SLIX/_decorators.py
SLIX/_logging.py
SLIX/_preparation.py
SLIX/_visualization.py
SLIX/attributemanager.py
SLIX/classification.py
SLIX/io.py
SLIX/parameters.py
SLIX/preparation.py
SLIX/toolbox.py
SLIX/visualization.py
SLIX/CPU/__init__.py
SLIX/CPU/_toolbox.py
SLIX/CPU/toolbox.py
SLIX/GPU/__init__.py
SLIX/GPU/_toolbox.py
SLIX/GPU/toolbox.py
SLIX/_cmd/Cluster.py
SLIX/_cmd/LineplotParameterGenerator.py
SLIX/_cmd/ParameterGenerator.py
SLIX/_cmd/VisualizeParameter.py
SLIX/_cmd/__init__.py
tests/__init__.py
tests/test_classification.py
tests/test_cmd_classification.py
tests/test_cmd_full_image.py
tests/test_cmd_line_profile.py
tests/test_compare_cpu_gpu.py
tests/test_io.py
tests/test_numba_toolbox_cpu.py
tests/test_numba_toolbox_gpu.py
tests/test_preparation.py
tests/test_toolbox.py
tests/test_visualization.py
SLIX-2.4.2.dist-info/LICENSE
SLIX-2.4.2.dist-info/METADATA
SLIX-2.4.2.dist-info/WHEEL
SLIX-2.4.2.dist-info/entry_points.txt
SLIX-2.4.2.dist-info/top_level.txt
SLIX-2.4.2.dist-info/RECORD
