Metadata-Version: 2.1
Name: SLIX
Version: 2.4.2
Summary: SLIX allows an automated evaluation of SLI measurements and generates different parameter maps.
Home-page: https://github.com/3d-pli/SLIX
Author: Jan Andre Reuter, Miriam Menzel
Author-email: j.reuter@fz-juelich.de, m.menzel@fz-juelich.de
License: MIT
Platform: UNKNOWN
Classifier: Programming Language :: Python :: 3
Classifier: License :: OSI Approved :: MIT License
Classifier: Operating System :: OS Independent
Requires-Python: >=3.6
License-File: LICENSE
Requires-Dist: appdirs
Requires-Dist: tifffile
Requires-Dist: numpy
Requires-Dist: nibabel
Requires-Dist: h5py
Requires-Dist: pillow
Requires-Dist: numba
Requires-Dist: matplotlib
Requires-Dist: tqdm
Requires-Dist: scipy
Requires-Dist: imagecodecs
